iblatlas/__init__.py
iblatlas/allen_structure_tree.csv
iblatlas/atlas.py
iblatlas/beryl.npy
iblatlas/cosmos.npy
iblatlas/flatmaps.py
iblatlas/franklin_paxinos_structure_tree.csv
iblatlas/mappings.pqt
iblatlas/plots.py
iblatlas/regions.py
iblatlas/swanson_regions.npy
iblatlas/genomics/__init__.py
iblatlas/genomics/agea.py
iblatlas/genomics/merfish.py
iblatlas/genomics/gene_expression_scrapping/01-make_experiments_parquet.py
iblatlas/genomics/gene_expression_scrapping/02-scrape-experiments.py
iblatlas/genomics/gene_expression_scrapping/03-scrape-correlations.py
iblatlas/genomics/gene_expression_scrapping/04-read-experiments.py
iblatlas/genomics/gene_expression_scrapping/05-generate-atlas-templates.py
iblatlas/genomics/gene_expression_scrapping/06-denoise-impute.py
iblatlas/genomics/merfish_scrapping/00_download_data.py
iblatlas/genomics/merfish_scrapping/01_ingest_zhuang.py
iblatlas/genomics/merfish_scrapping/02_create_volumes.py
iblatlas/gui/__init__.py
iblatlas/gui/atlas_gui.ui
iblatlas/gui/atlasview.py
iblatlas/gui/braintree.py
iblatlas/gui/requirements.txt
iblatlas/gui/sliceview.ui
iblatlas/gui/topview.ui
iblatlas/streamlines/__init__.py
iblatlas/streamlines/utils.py
iblatlas/streamlines/streamlines_scraping/prepare_depths.py
iblatlas/streamlines/streamlines_scraping/prepare_laplacian.py
iblatlas/streamlines/streamlines_scraping/prepare_streamlines.py
iblatlas/tests/__init__.py
iblatlas/tests/test_allen_atlas.py
iblatlas/tests/test_atlas.py
iblatlas/tests/test_genomics.py
iblatlas-0.10.0.dist-info/licenses/LICENSE
iblatlas-0.10.0.dist-info/METADATA
iblatlas-0.10.0.dist-info/WHEEL
iblatlas-0.10.0.dist-info/entry_points.txt
iblatlas-0.10.0.dist-info/top_level.txt
iblatlas-0.10.0.dist-info/RECORD
