Metadata-Version: 2.4
Name: iblatlas
Version: 0.10.0
Summary: IBL atlas module
Author-email: IBL staff <info@internationalbrainlab.org>
License: MIT License
Project-URL: Homepage, https://github.com/int-brain-lab/iblatlas
Project-URL: Documentation, https://github.com/int-brain-lab/iblatlas/tree/main/examples
Project-URL: ChangeLog, https://github.com/int-brain-lab/iblatlas/blob/main/CHANGELOG.md
Project-URL: Bug Tracker, https://github.com/int-brain-lab/iblatlas/issues
Classifier: Programming Language :: Python :: 3
Classifier: License :: OSI Approved :: MIT License
Classifier: Operating System :: OS Independent
Requires-Python: >=3.10
License-File: LICENSE
Requires-Dist: ONE-api
Requires-Dist: iblutil
Requires-Dist: pynrrd
Requires-Dist: numpy
Requires-Dist: matplotlib
Requires-Dist: scipy
Provides-Extra: gui
Requires-Dist: pyqt5; extra == "gui"
Requires-Dist: qtpy; extra == "gui"
Dynamic: license-file
